optimade_maker/__init__.py
optimade_maker/cli.py
optimade_maker/config.py
optimade_maker/convert.py
optimade_maker/logger.py
optimade_maker/mongo_utils.py
optimade_maker/parsers.py
optimade_maker/serve.py
optimade_maker/aiida_plugin/__init__.py
optimade_maker/aiida_plugin/config.py
optimade_maker-0.7.0.dist-info/licenses/LICENSE
optimade_maker-0.7.0.dist-info/METADATA
optimade_maker-0.7.0.dist-info/WHEEL
optimade_maker-0.7.0.dist-info/entry_points.txt
optimade_maker-0.7.0.dist-info/top_level.txt
optimade_maker-0.7.0.dist-info/RECORD
