Metadata-Version: 2.4
Name: optimade-maker
Version: 0.7.0
Summary: Tools for making OPTIMADE APIs from raw structural data.
License: MIT
Keywords: optimade,jsonapi,materials
Classifier: Development Status :: 4 - Beta
Classifier: Programming Language :: Python :: 3 :: Only
Classifier: Programming Language :: Python :: 3.10
Classifier: Programming Language :: Python :: 3.11
Classifier: Programming Language :: Python :: 3.12
Classifier: Intended Audience :: Science/Research
Classifier: Topic :: Database
Classifier: Topic :: Scientific/Engineering
Requires-Python: <3.13,>=3.10
License-File: LICENSE
Requires-Dist: pydantic~=2.2
Requires-Dist: optimade[server]~=1.3
Requires-Dist: pymongo
Requires-Dist: pyyaml~=6.0
Requires-Dist: tqdm~=4.65
Requires-Dist: requests~=2.31
Requires-Dist: numpy<3,>=1.22
Requires-Dist: click~=8.1
Provides-Extra: ase
Requires-Dist: ase~=3.22; extra == "ase"
Provides-Extra: pymatgen
Requires-Dist: pymatgen>=2023.9; extra == "pymatgen"
Provides-Extra: pandas
Requires-Dist: pandas<3,>=1.5; extra == "pandas"
Provides-Extra: aiida
Requires-Dist: aiida-core>=2.6.3; extra == "aiida"
Provides-Extra: core
Requires-Dist: optimade-maker[ase,pandas,pymatgen]; extra == "core"
Provides-Extra: ingest
Requires-Dist: optimade-maker[aiida,ase,pandas,pymatgen]; extra == "ingest"
Provides-Extra: tests
Requires-Dist: pytest~=8.3; extra == "tests"
Requires-Dist: pytest-cov~=6.0; extra == "tests"
Provides-Extra: dev
Requires-Dist: ruff; extra == "dev"
Requires-Dist: pre-commit; extra == "dev"
Requires-Dist: mypy; extra == "dev"
Dynamic: license-file
